fbprophet_inference/__init__.py
fbprophet_inference/diagnostics.py
fbprophet_inference/forecaster.py
fbprophet_inference/hdays.py
fbprophet_inference/make_holidays.py
fbprophet_inference/models.py
fbprophet_inference/plot.py
fbprophet_inference/serialize.py
fbprophet_inference/tests/__init__.py
fbprophet_inference/tests/test_diagnostics.py
fbprophet_inference/tests/test_prophet.py
fbprophet_inference/tests/test_serialize.py
fbprophet_inference-0.7.dist-info/LICENSE
fbprophet_inference-0.7.dist-info/METADATA
fbprophet_inference-0.7.dist-info/WHEEL
fbprophet_inference-0.7.dist-info/top_level.txt
fbprophet_inference-0.7.dist-info/zip-safe
fbprophet_inference-0.7.dist-info/RECORD
